Workbook

Sheet Annahmen
A1: Parameter | B1: Wert | C1: Quelle / Hinweis
A2: Kurs (USD, ca. 14.10.2026) | B2: 223.72 | C2: Yahoo Finance (Vortagesschluss 220,79) ⚠
A3: Aktien verwässert (Mio.) | B3: 173 | C3: Annahme der FY27-Guidance (voll verwässert)
A4: Nettoliquidität (Mio. USD, positiv = mehr Cash als Schulden) | B4: 1900 | C4: GESCHÄTZT: Cash ~3,6 Mrd. – Wandelanleihe 1,725 Mrd. (fällig 2028)
A5: Umsatz FY2026 (Mio. USD, GJ bis 31.07.2026) | B5: 3353 | C5: Q4-Pressemitteilung FY2026
A6: Umsatz FY2027E Guidance (Mio. USD) | B6: 3923 | C6: Mitte 3,908–3,938 Mrd.
A7: Non-GAAP operative Marge FY2027E | B7: 0.23 | C7: GESCHÄTZT (Q4 FY26: 24,3 %)
A8: Abschreibungen in % Umsatz (für EBITDA) | B8: 0.07 | C8: GESCHÄTZT (hohe Investitionen in Rechenzentren)
A9: Non-GAAP EPS FY2027E (USD) | B9: 4.88 | C9: Mitte 4,86–4,90
A10: Bereinigte FCF-Marge FY2027E | B10: 0.2325 | C10: Guidance 23,0–23,5 %
A11: Aktienvergütung (SBC) in % Umsatz | B11: 0.2 | C11: GESCHÄTZT (FY25/26 ~21–22 %)
A12: SBC vom FCF abziehen? (1 = ja, 0 = nein) | B12: 1 | C12: Konservativ: Aktienvergütung ist echter Aufwand
A13: Dividende je Aktie (USD) | B13: 0 | C13: keine Dividende
A15: Marktkapitalisierung (Mio.) | B15: =B2*B3 -> 38703.56
A16: Enterprise Value (Mio.) | B16: =B15-B4 -> 36803.56
A17: KGV FY2027E (Non-GAAP) | B17: =B2/B9 -> 45.844262
A18: EV/EBITDA FY2027E (bereinigt) | B18: =B16/(B6*(B7+B8)) -> 31.271612
A19: EV/Umsatz FY2027E | B19: =B16/B6 -> 9.3814836
A20: FCF-Rendite (bereinigt) | B20: =B6*B10/B15 -> 0.023566243
A21: FCF-Rendite nach SBC | B21: =B6*(B10-B11)/B15 -> 0.003294206
A22: Dividendenrendite | B22: =B13/B2 -> 0

Sheet Historie
A1: Mio. USD (GJ endet 31. Juli) | B1: FY2022 | C1: FY2023 | D1: FY2024 | E1: FY2025 | F1: FY2026
A2: Umsatz | B2: 1091 | C2: 1617 | D2: 2168 | E2: 2673 | F2: 3353
A3: Nettogewinn GAAP | B3: -390 | C3: -202 | D3: -58 | E3: -42 | F3: -30
A4: EPS Non-GAAP (USD) | B4: 0.84 | C4: 1.89 | D4: 2.96 | E4: 3.28 | F4: 4.21
A5: Free Cashflow | B5: 313 | C5: 456 | D5: 640 | E5: 727 | F5: 779
A6: Dividende je Aktie (USD) | B6: 0 | C6: 0 | D6: 0 | E6: 0 | F6: 0
A7: Nettomarge GAAP | B7: =B3/B2 -> -0.35747021 | C7: =C3/C2 -> -0.1249227 | D7: =D3/D2 -> -0.026752768 | E7: =E3/E2 -> -0.015712682 | F7: =F3/F2 -> -0.0089472115
A8: FCF-Marge | B8: =B5/B2 -> 0.28689276 | C8: =C5/C2 -> 0.28200371 | D8: =D5/D2 -> 0.29520295 | E8: =E5/E2 -> 0.27197905 | F8: =F5/F2 -> 0.23232926
A9: Umsatzwachstum | C9: =C2/B2-1 -> 0.48212649 | D9: =D2/C2-1 -> 0.34075448 | E9: =E2/D2-1 -> 0.23293358 | F9: =F2/E2-1 -> 0.25439581
A11: Hinweise: FY2026 = Aug. 2025 bis Juli 2026, inkl. Red Canary (gekauft 01.08.2025 für 675 Mio. USD). GAAP-Nettogewinn FY2025/FY2026 GESCHÄTZT. Non-GAAP-EPS FY2022–FY2024 und FCF FY2022–FY2024 aus Gedächtnis rekonstruiert (±5 %).

Sheet DCF
A1: Szenario: Pessimistisch
A2: WACC | B2: 0.105
A3: Ewiges Wachstum | B3: 0.03
B4: FY2028E | C4: FY2029E | D4: FY2030E | E4: FY2031E | F4: FY2032E | G4: FY2033E | H4: FY2034E | I4: FY2035E | J4: FY2036E | K4: FY2037E
A5: Umsatzwachstum | B5: 0.14 | C5: 0.12 | D5: 0.1 | E5: 0.09 | F5: 0.08 | G5: 0.07 | H5: 0.06 | I5: 0.05 | J5: 0.05 | K5: 0.04
A6: Umsatz | B6: =Annahmen!B6*(1+B5) -> 4472.22 | C6: =B6*(1+C5) -> 5008.8864 | D6: =C6*(1+D5) -> 5509.775 | E6: =D6*(1+E5) -> 6005.6548 | F6: =E6*(1+F5) -> 6486.1072 | G6: =F6*(1+G5) -> 6940.1347 | H6: =G6*(1+H5) -> 7356.5428 | I6: =H6*(1+I5) -> 7724.3699 | J6: =I6*(1+J5) -> 8110.5884 | K6: =J6*(1+K5) -> 8435.0119
A7: FCF-Marge nach SBC | B7: =0.04+(1-Annahmen!$B$12)*Annahmen!$B$11 -> 0.04 | C7: =0.055+(1-Annahmen!$B$12)*Annahmen!$B$11 -> 0.055 | D7: =0.07+(1-Annahmen!$B$12)*Annahmen!$B$11 -> 0.07 | E7: =0.085+(1-Annahmen!$B$12)*Annahmen!$B$11 -> 0.085 | F7: =0.1+(1-Annahmen!$B$12)*Annahmen!$B$11 -> 0.1 | G7: =0.115+(1-Annahmen!$B$12)*Annahmen!$B$11 -> 0.115 | H7: =0.13+(1-Annahmen!$B$12)*Annahmen!$B$11 -> 0.13 | I7: =0.15+(1-Annahmen!$B$12)*Annahmen!$B$11 -> 0.15 | J7: =0.165+(1-Annahmen!$B$12)*Annahmen!$B$11 -> 0.165 | K7: =0.18+(1-Annahmen!$B$12)*Annahmen!$B$11 -> 0.18
A8: Free Cashflow (nach SBC) | B8: =B6*B7 -> 178.8888 | C8: =C6*C7 -> 275.48875 | D8: =D6*D7 -> 385.68425 | E8: =E6*E7 -> 510.48066 | F8: =F6*F7 -> 648.61072 | G8: =G6*G7 -> 798.11549 | H8: =H6*H7 -> 956.35056 | I8: =I6*I7 -> 1158.6555 | ... K8: =K6*K7 -> 1518.3021
A9: Abzinsungsfaktor | B9: =1/(1+$B$2)^(0+0.8) -> 0.92323057 | C9: =1/(1+$B$2)^(1+0.8) -> 0.83550278 | D9: =1/(1+$B$2)^(2+0.8) -> 0.75611111 | E9: =1/(1+$B$2)^(3+0.8) -> 0.68426345 | F9: =1/(1+$B$2)^(4+0.8) -> 0.61924294 | G9: =1/(1+$B$2)^(5+0.8) -> 0.56040085 | H9: =1/(1+$B$2)^(6+0.8) -> 0.50715009 | I9: =1/(1+$B$2)^(7+0.8) -> 0.45895936 | J9: =1/(1+$B$2)^(8+0.8) -> 0.41534784 | K9: =1/(1+$B$2)^(9+0.8) -> 0.3758804
A10: Barwert FCF | B10: =B8*B9 -> 165.15561 | C10: =C8*C9 -> 230.17162 | D10: =D8*D9 -> 291.62015 | E10: =E8*E9 -> 349.30326 | F10: =F8*F9 -> 401.64761 | G10: =G8*G9 -> 447.2646 | H10: =H8*H9 -> 485.01327 | I10: =I8*I9 -> 531.77578 | ... K10: =K8*K9 -> 570.70001
A11: Summe Barwerte FCF | B11: =SUM(B10:K10) -> 4028.4899
A12: Endwert (Terminal Value) | B12: =K8*(1+B3)/(B2-B3) -> 20851.349
A13: Barwert Endwert | B13: =B12*K9 -> 7837.6135
A14: Enterprise Value | B14: =B11+B13 -> 11866.103
A15: + Nettoliquidität | B15: =Annahmen!B4 -> 1900
A16: Eigenkapitalwert | B16: =B14+B15 -> 13766.103
A17: Fairer Wert je Aktie (USD) | B17: =B16/Annahmen!B3 -> 79.572852
A18: Abstand zum Kurs | B18: =B17/Annahmen!B2-1 -> -0.64431945
A19: Anteil Endwert am EV | B19: =B13/B14 -> 0.6605044
A22: Szenario: Realistisch
A23: WACC | B23: 0.095
A24: Ewiges Wachstum | B24: 0.035
B25: FY2028E | C25: FY2029E | D25: FY2030E | E25: FY2031E | F25: FY2032E | G25: FY2033E | H25: FY2034E | I25: FY2035E | J25: FY2036E | K25: FY2037E
A26: Umsatzwachstum | B26: 0.17 | C26: 0.16 | D26: 0.15 | E26: 0.14 | F26: 0.12 | G26: 0.11 | H26: 0.1 | I26: 0.09 | J26: 0.08 | K26: 0.07
A27: Umsatz | B27: =Annahmen!B6*(1+B26) -> 4589.91 | C27: =B27*(1+C26) -> 5324.2956 | D27: =C27*(1+D26) -> 6122.9399 | E27: =D27*(1+E26) -> 6980.1515 | F27: =E27*(1+F26) -> 7817.7697 | G27: =F27*(1+G26) -> 8677.7244 | H27: =G27*(1+H26) -> 9545.4968 | I27: =H27*(1+I26) -> 10404.592 | J27: =I27*(1+J26) -> 11236.959 | K27: =J27*(1+K26) -> 12023.546
A28: FCF-Marge nach SBC | B28: =0.05+(1-Annahmen!$B$12)*Annahmen!$B$11 -> 0.05 | C28: =0.07+(1-Annahmen!$B$12)*Annahmen!$B$11 -> 0.07 | D28: =0.09+(1-Annahmen!$B$12)*Annahmen!$B$11 -> 0.09 | E28: =0.11+(1-Annahmen!$B$12)*Annahmen!$B$11 -> 0.11 | F28: =0.13+(1-Annahmen!$B$12)*Annahmen!$B$11 -> 0.13 | G28: =0.15+(1-Annahmen!$B$12)*Annahmen!$B$11 -> 0.15 | H28: =0.18+(1-Annahmen!$B$12)*Annahmen!$B$11 -> 0.18 | I28: =0.21+(1-Annahmen!$B$12)*Annahmen!$B$11 -> 0.21 | J28: =0.23+(1-Annahmen!$B$12)*Annahmen!$B$11 -> 0.23 | K28: =0.25+(1-Annahmen!$B$12)*Annahmen!$B$11 -> 0.25
A29: Free Cashflow (nach SBC) | B29: =B27*B28 -> 229.4955 | C29: =C27*C28 -> 372.70069 | D29: =D27*D28 -> 551.06459 | E29: =E27*E28 -> 767.81667 | F29: =F27*F28 -> 1016.3101 | G29: =G27*G28 -> 1301.6587 | H29: =H27*H28 -> 1718.1894 | I29: =I27*I28 -> 2184.9642 | ... K29: =K27*K28 -> 3005.8865
A30: Abzinsungsfaktor | B30: =1/(1+$B$23)^(0+0.8) -> 0.9299695 | C30: =1/(1+$B$23)^(1+0.8) -> 0.84928721 | D30: =1/(1+$B$23)^(2+0.8) -> 0.77560476 | E30: =1/(1+$B$23)^(3+0.8) -> 0.70831485 | F30: =1/(1+$B$23)^(4+0.8) -> 0.64686288 | G30: =1/(1+$B$23)^(5+0.8) -> 0.59074235 | H30: =1/(1+$B$23)^(6+0.8) -> 0.53949073 | I30: =1/(1+$B$23)^(7+0.8) -> 0.4926856 | J30: =1/(1+$B$23)^(8+0.8) -> 0.44994119 | K30: =1/(1+$B$23)^(9+0.8) -> 0.4109052
A31: Barwert FCF | B31: =B29*B30 -> 213.42382 | C31: =C29*C30 -> 316.52993 | D31: =D29*D30 -> 427.40832 | E31: =E29*E30 -> 543.85595 | F31: =F29*F30 -> 657.41325 | G31: =G29*G30 -> 768.9449 | H31: =H29*H30 -> 926.94728 | I31: =I29*I30 -> 1076.5004 | ... K31: =K29*K30 -> 1235.1344
A32: Summe Barwerte FCF | B32: =SUM(B31:K31) -> 7329.0315
A33: Endwert (Terminal Value) | B33: =K29*(1+B24)/(B23-B24) -> 51851.542
A34: Barwert Endwert | B34: =B33*K30 -> 21306.068
A35: Enterprise Value | B35: =B32+B34 -> 28635.099
A36: + Nettoliquidität | B36: =Annahmen!B4 -> 1900
A37: Eigenkapitalwert | B37: =B35+B36 -> 30535.099
A38: Fairer Wert je Aktie (USD) | B38: =B37/Annahmen!B3 -> 176.50347
A39: Abstand zum Kurs | B39: =B38/Annahmen!B2-1 -> -0.21105192
A40: Anteil Endwert am EV | B40: =B34/B35 -> 0.74405427
A43: Szenario: Optimistisch
A44: WACC | B44: 0.09
A45: Ewiges Wachstum | B45: 0.04
B46: FY2028E | C46: FY2029E | D46: FY2030E | E46: FY2031E | F46: FY2032E | G46: FY2033E | H46: FY2034E | I46: FY2035E | J46: FY2036E | K46: FY2037E
A47: Umsatzwachstum | B47: 0.19 | C47: 0.19 | D47: 0.18 | E47: 0.17 | F47: 0.15 | G47: 0.14 | H47: 0.12 | I47: 0.11 | J47: 0.1 | K47: 0.08
A48: Umsatz | B48: =Annahmen!B6*(1+B47) -> 4668.37 | C48: =B48*(1+C47) -> 5555.3603 | D48: =C48*(1+D47) -> 6555.3252 | E48: =D48*(1+E47) -> 7669.7304 | F48: =E48*(1+F47) -> 8820.19 | G48: =F48*(1+G47) -> 10055.017 | H48: =G48*(1+H47) -> 11261.619 | I48: =H48*(1+I47) -> 12500.397 | J48: =I48*(1+J47) -> 13750.436 | K48: =J48*(1+K47) -> 14850.471
A49: FCF-Marge nach SBC | B49: =0.06+(1-Annahmen!$B$12)*Annahmen!$B$11 -> 0.06 | C49: =0.085+(1-Annahmen!$B$12)*Annahmen!$B$11 -> 0.085 | D49: =0.11+(1-Annahmen!$B$12)*Annahmen!$B$11 -> 0.11 | E49: =0.135+(1-Annahmen!$B$12)*Annahmen!$B$11 -> 0.135 | F49: =0.16+(1-Annahmen!$B$12)*Annahmen!$B$11 -> 0.16 | G49: =0.19+(1-Annahmen!$B$12)*Annahmen!$B$11 -> 0.19 | H49: =0.22+(1-Annahmen!$B$12)*Annahmen!$B$11 -> 0.22 | I49: =0.25+(1-Annahmen!$B$12)*Annahmen!$B$11 -> 0.25 | J49: =0.28+(1-Annahmen!$B$12)*Annahmen!$B$11 -> 0.28 | K49: =0.3+(1-Annahmen!$B$12)*Annahmen!$B$11 -> 0.3
A50: Free Cashflow (nach SBC) | B50: =B48*B49 -> 280.1022 | C50: =C48*C49 -> 472.20563 | D50: =D48*D49 -> 721.08577 | E50: =E48*E49 -> 1035.4136 | F50: =F48*F49 -> 1411.2304 | G50: =G48*G49 -> 1910.4532 | H50: =H48*H49 -> 2477.5561 | I50: =I48*I49 -> 3125.0992 | ... K50: =K48*K49 -> 4455.1414
A51: Abzinsungsfaktor | B51: =1/(1+$B$44)^(0+0.8) -> 0.93338067 | C51: =1/(1+$B$44)^(1+0.8) -> 0.85631254 | D51: =1/(1+$B$44)^(2+0.8) -> 0.78560783 | E51: =1/(1+$B$44)^(3+0.8) -> 0.72074113 | F51: =1/(1+$B$44)^(4+0.8) -> 0.6612304 | G51: =1/(1+$B$44)^(5+0.8) -> 0.60663339 | H51: =1/(1+$B$44)^(6+0.8) -> 0.5565444 | I51: =1/(1+$B$44)^(7+0.8) -> 0.51059119 | J51: =1/(1+$B$44)^(8+0.8) -> 0.46843228 | K51: =1/(1+$B$44)^(9+0.8) -> 0.42975439
A52: Barwert FCF | B52: =B50*B51 -> 261.44198 | C52: =C50*C51 -> 404.3556 | D52: =D50*D51 -> 566.49063 | E52: =E50*E51 -> 746.26518 | F52: =F50*F51 -> 933.14844 | G52: =G50*G51 -> 1158.9447 | H52: =H50*H51 -> 1378.87 | I52: =I50*I51 -> 1595.6481 | ... K52: =K50*K51 -> 1914.6166
A53: Summe Barwerte FCF | B53: =SUM(B52:K52) -> 10763.303
A54: Endwert (Terminal Value) | B54: =K50*(1+B45)/(B44-B45) -> 92666.94
A55: Barwert Endwert | B55: =B54*K51 -> 39824.024
A56: Enterprise Value | B56: =B53+B55 -> 50587.327
A57: + Nettoliquidität | B57: =Annahmen!B4 -> 1900
A58: Eigenkapitalwert | B58: =B56+B57 -> 52487.327
A59: Fairer Wert je Aktie (USD) | B59: =B58/Annahmen!B3 -> 303.39495
A60: Abstand zum Kurs | B60: =B59/Annahmen!B2-1 -> 0.35613693
A61: Anteil Endwert am EV | B61: =B55/B56 -> 0.78723322
A64: Zusammenfassung
A65: Pessimistisch | B65: =B17 -> 79.572852 | C65: =B18 -> -0.64431945
A66: Realistisch | B66: =B38 -> 176.50347 | C66: =B39 -> -0.21105192
A67: Optimistisch | B67: =B59 -> 303.39495 | C67: =B60 -> 0.35613693
A68: Gewichtet (25/50/25) | B68: =0.25*B65+0.5*B66+0.25*B67 -> 183.99368
A70: Bewertungsstichtag Mitte Okt. 2026; Basis = Umsatz-Guidance FY2027 (GJ bis 31.07.2027), Prognose FY2028–FY2037. FCF nach Abzug der Aktienvergütung (SBC); Schalter in Annahmen!B12. FCF-Marge ohne SBC-Abzug = Marge + 20 %-Punkte.
A72: Sensitivität Realistisch: Fairer Wert je Aktie (Zeilen WACC, Spalten ewiges Wachstum)
B73: 0.025 | C73: 0.03 | D73: 0.035 | E73: 0.04 | F73: 0.045
A74: 0.085 | B74: =((B29/(1+$A74)^(0+0.8)+C29/(1+$A74)^(1+0.8)+D29/(1+$A74)^(2+0.8)+E29/(1+$A74)^(3+0.8)+F29/(1+$A74)^(4+0.8)+G29/(1+$A74)^(5+0.8)+H29/(1+$A74)^(6+0.8)+I29/(1+$A74)^(7+0.8)+J29/(1+$A74)^(8+0.8)+K29/(1+$A74)^(9+0.8))+K29*(1+B$73)/($A74-B$73)/(1+$A74)^9.8+Annahmen!B4)/Annahmen!B3 -> 189.46023 | C74: =((B29/(1+$A74)^(0+0.8)+C29/(1+$A74)^(1+0.8)+D29/(1+$A74)^(2+0.8)+E29/(1+$A74)^(3+0.8)+F29/(1+$A74)^(4+0.8)+G29/(1+$A74)^(5+0.8)+H29/(1+$A74)^(6+0.8)+I29/(1+$A74)^(7+0.8)+J29/(1+$A74)^(8+0.8)+K29/(1+$A74)^(9+0.8))+K29*(1+C$73)/($A74-C$73)/(1+$A74)^9.8+Annahmen!B4)/Annahmen!B3 -> 202.30129 | D74: =((B29/(1+$A74)^(0+0.8)+C29/(1+$A74)^(1+0.8)+D29/(1+$A74)^(2+0.8)+E29/(1+$A74)^(3+0.8)+F29/(1+$A74)^(4+0.8)+G29/(1+$A74)^(5+0.8)+H29/(1+$A74)^(6+0.8)+I29/(1+$A74)^(7+0.8)+J29/(1+$A74)^(8+0.8)+K29/(1+$A74)^(9+0.8))+K29*(1+D$73)/($A74-D$73)/(1+$A74)^9.8+Annahmen!B4)/Annahmen!B3 -> 217.71056 | E74: =((B29/(1+$A74)^(0+0.8)+C29/(1+$A74)^(1+0.8)+D29/(1+$A74)^(2+0.8)+E29/(1+$A74)^(3+0.8)+F29/(1+$A74)^(4+0.8)+G29/(1+$A74)^(5+0.8)+H29/(1+$A74)^(6+0.8)+I29/(1+$A74)^(7+0.8)+J29/(1+$A74)^(8+0.8)+K29/(1+$A74)^(9+0.8))+K29*(1+E$73)/($A74-E$73)/(1+$A74)^9.8+Annahmen!B4)/Annahmen!B3 -> 236.54411 | F74: =((B29/(1+$A74)^(0+0.8)+C29/(1+$A74)^(1+0.8)+D29/(1+$A74)^(2+0.8)+E29/(1+$A74)^(3+0.8)+F29/(1+$A74)^(4+0.8)+G29/(1+$A74)^(5+0.8)+H29/(1+$A74)^(6+0.8)+I29/(1+$A74)^(7+0.8)+J29/(1+$A74)^(8+0.8)+K29/(1+$A74)^(9+0.8))+K29*(1+F$73)/($A74-F$73)/(1+$A74)^9.8+Annahmen!B4)/Annahmen!B3 -> 260.08605
A75: 0.09 | B75: =((B29/(1+$A75)^(0+0.8)+C29/(1+$A75)^(1+0.8)+D29/(1+$A75)^(2+0.8)+E29/(1+$A75)^(3+0.8)+F29/(1+$A75)^(4+0.8)+G29/(1+$A75)^(5+0.8)+H29/(1+$A75)^(6+0.8)+I29/(1+$A75)^(7+0.8)+J29/(1+$A75)^(8+0.8)+K29/(1+$A75)^(9+0.8))+K29*(1+B$73)/($A75-B$73)/(1+$A75)^9.8+Annahmen!B4)/Annahmen!B3 -> 172.40593 | C75: =((B29/(1+$A75)^(0+0.8)+C29/(1+$A75)^(1+0.8)+D29/(1+$A75)^(2+0.8)+E29/(1+$A75)^(3+0.8)+F29/(1+$A75)^(4+0.8)+G29/(1+$A75)^(5+0.8)+H29/(1+$A75)^(6+0.8)+I29/(1+$A75)^(7+0.8)+J29/(1+$A75)^(8+0.8)+K29/(1+$A75)^(9+0.8))+K29*(1+C$73)/($A75-C$73)/(1+$A75)^9.8+Annahmen!B4)/Annahmen!B3 -> 182.8406 | D75: =((B29/(1+$A75)^(0+0.8)+C29/(1+$A75)^(1+0.8)+D29/(1+$A75)^(2+0.8)+E29/(1+$A75)^(3+0.8)+F29/(1+$A75)^(4+0.8)+G29/(1+$A75)^(5+0.8)+H29/(1+$A75)^(6+0.8)+I29/(1+$A75)^(7+0.8)+J29/(1+$A75)^(8+0.8)+K29/(1+$A75)^(9+0.8))+K29*(1+D$73)/($A75-D$73)/(1+$A75)^9.8+Annahmen!B4)/Annahmen!B3 -> 195.17248 | E75: =((B29/(1+$A75)^(0+0.8)+C29/(1+$A75)^(1+0.8)+D29/(1+$A75)^(2+0.8)+E29/(1+$A75)^(3+0.8)+F29/(1+$A75)^(4+0.8)+G29/(1+$A75)^(5+0.8)+H29/(1+$A75)^(6+0.8)+I29/(1+$A75)^(7+0.8)+J29/(1+$A75)^(8+0.8)+K29/(1+$A75)^(9+0.8))+K29*(1+E$73)/($A75-E$73)/(1+$A75)^9.8+Annahmen!B4)/Annahmen!B3 -> 209.97074 | F75: =((B29/(1+$A75)^(0+0.8)+C29/(1+$A75)^(1+0.8)+D29/(1+$A75)^(2+0.8)+E29/(1+$A75)^(3+0.8)+F29/(1+$A75)^(4+0.8)+G29/(1+$A75)^(5+0.8)+H29/(1+$A75)^(6+0.8)+I29/(1+$A75)^(7+0.8)+J29/(1+$A75)^(8+0.8)+K29/(1+$A75)^(9+0.8))+K29*(1+F$73)/($A75-F$73)/(1+$A75)^9.8+Annahmen!B4)/Annahmen!B3 -> 228.0575
A76: 0.095 | B76: =((B29/(1+$A76)^(0+0.8)+C29/(1+$A76)^(1+0.8)+D29/(1+$A76)^(2+0.8)+E29/(1+$A76)^(3+0.8)+F29/(1+$A76)^(4+0.8)+G29/(1+$A76)^(5+0.8)+H29/(1+$A76)^(6+0.8)+I29/(1+$A76)^(7+0.8)+J29/(1+$A76)^(8+0.8)+K29/(1+$A76)^(9+0.8))+K29*(1+B$73)/($A76-B$73)/(1+$A76)^9.8+Annahmen!B4)/Annahmen!B3 -> 157.88976 | C76: =((B29/(1+$A76)^(0+0.8)+C29/(1+$A76)^(1+0.8)+D29/(1+$A76)^(2+0.8)+E29/(1+$A76)^(3+0.8)+F29/(1+$A76)^(4+0.8)+G29/(1+$A76)^(5+0.8)+H29/(1+$A76)^(6+0.8)+I29/(1+$A76)^(7+0.8)+J29/(1+$A76)^(8+0.8)+K29/(1+$A76)^(9+0.8))+K29*(1+C$73)/($A76-C$73)/(1+$A76)^9.8+Annahmen!B4)/Annahmen!B3 -> 166.4807 | D76: =((B29/(1+$A76)^(0+0.8)+C29/(1+$A76)^(1+0.8)+D29/(1+$A76)^(2+0.8)+E29/(1+$A76)^(3+0.8)+F29/(1+$A76)^(4+0.8)+G29/(1+$A76)^(5+0.8)+H29/(1+$A76)^(6+0.8)+I29/(1+$A76)^(7+0.8)+J29/(1+$A76)^(8+0.8)+K29/(1+$A76)^(9+0.8))+K29*(1+D$73)/($A76-D$73)/(1+$A76)^9.8+Annahmen!B4)/Annahmen!B3 -> 176.50347 | E76: =((B29/(1+$A76)^(0+0.8)+C29/(1+$A76)^(1+0.8)+D29/(1+$A76)^(2+0.8)+E29/(1+$A76)^(3+0.8)+F29/(1+$A76)^(4+0.8)+G29/(1+$A76)^(5+0.8)+H29/(1+$A76)^(6+0.8)+I29/(1+$A76)^(7+0.8)+J29/(1+$A76)^(8+0.8)+K29/(1+$A76)^(9+0.8))+K29*(1+E$73)/($A76-E$73)/(1+$A76)^9.8+Annahmen!B4)/Annahmen!B3 -> 188.34855 | F76: =((B29/(1+$A76)^(0+0.8)+C29/(1+$A76)^(1+0.8)+D29/(1+$A76)^(2+0.8)+E29/(1+$A76)^(3+0.8)+F29/(1+$A76)^(4+0.8)+G29/(1+$A76)^(5+0.8)+H29/(1+$A76)^(6+0.8)+I29/(1+$A76)^(7+0.8)+J29/(1+$A76)^(8+0.8)+K29/(1+$A76)^(9+0.8))+K29*(1+F$73)/($A76-F$73)/(1+$A76)^9.8+Annahmen!B4)/Annahmen!B3 -> 202.56266
A77: 0.1 | B77: =((B29/(1+$A77)^(0+0.8)+C29/(1+$A77)^(1+0.8)+D29/(1+$A77)^(2+0.8)+E29/(1+$A77)^(3+0.8)+F29/(1+$A77)^(4+0.8)+G29/(1+$A77)^(5+0.8)+H29/(1+$A77)^(6+0.8)+I29/(1+$A77)^(7+0.8)+J29/(1+$A77)^(8+0.8)+K29/(1+$A77)^(9+0.8))+K29*(1+B$73)/($A77-B$73)/(1+$A77)^9.8+Annahmen!B4)/Annahmen!B3 -> 145.40031 | C77: =((B29/(1+$A77)^(0+0.8)+C29/(1+$A77)^(1+0.8)+D29/(1+$A77)^(2+0.8)+E29/(1+$A77)^(3+0.8)+F29/(1+$A77)^(4+0.8)+G29/(1+$A77)^(5+0.8)+H29/(1+$A77)^(6+0.8)+I29/(1+$A77)^(7+0.8)+J29/(1+$A77)^(8+0.8)+K29/(1+$A77)^(9+0.8))+K29*(1+C$73)/($A77-C$73)/(1+$A77)^9.8+Annahmen!B4)/Annahmen!B3 -> 152.5532 | D77: =((B29/(1+$A77)^(0+0.8)+C29/(1+$A77)^(1+0.8)+D29/(1+$A77)^(2+0.8)+E29/(1+$A77)^(3+0.8)+F29/(1+$A77)^(4+0.8)+G29/(1+$A77)^(5+0.8)+H29/(1+$A77)^(6+0.8)+I29/(1+$A77)^(7+0.8)+J29/(1+$A77)^(8+0.8)+K29/(1+$A77)^(9+0.8))+K29*(1+D$73)/($A77-D$73)/(1+$A77)^9.8+Annahmen!B4)/Annahmen!B3 -> 160.80654 | E77: =((B29/(1+$A77)^(0+0.8)+C29/(1+$A77)^(1+0.8)+D29/(1+$A77)^(2+0.8)+E29/(1+$A77)^(3+0.8)+F29/(1+$A77)^(4+0.8)+G29/(1+$A77)^(5+0.8)+H29/(1+$A77)^(6+0.8)+I29/(1+$A77)^(7+0.8)+J29/(1+$A77)^(8+0.8)+K29/(1+$A77)^(9+0.8))+K29*(1+E$73)/($A77-E$73)/(1+$A77)^9.8+Annahmen!B4)/Annahmen!B3 -> 170.43543 | F77: =((B29/(1+$A77)^(0+0.8)+C29/(1+$A77)^(1+0.8)+D29/(1+$A77)^(2+0.8)+E29/(1+$A77)^(3+0.8)+F29/(1+$A77)^(4+0.8)+G29/(1+$A77)^(5+0.8)+H29/(1+$A77)^(6+0.8)+I29/(1+$A77)^(7+0.8)+J29/(1+$A77)^(8+0.8)+K29/(1+$A77)^(9+0.8))+K29*(1+F$73)/($A77-F$73)/(1+$A77)^9.8+Annahmen!B4)/Annahmen!B3 -> 181.81502
A78: 0.105 | B78: =((B29/(1+$A78)^(0+0.8)+C29/(1+$A78)^(1+0.8)+D29/(1+$A78)^(2+0.8)+E29/(1+$A78)^(3+0.8)+F29/(1+$A78)^(4+0.8)+G29/(1+$A78)^(5+0.8)+H29/(1+$A78)^(6+0.8)+I29/(1+$A78)^(7+0.8)+J29/(1+$A78)^(8+0.8)+K29/(1+$A78)^(9+0.8))+K29*(1+B$73)/($A78-B$73)/(1+$A78)^9.8+Annahmen!B4)/Annahmen!B3 -> 134.55422 | C78: =((B29/(1+$A78)^(0+0.8)+C29/(1+$A78)^(1+0.8)+D29/(1+$A78)^(2+0.8)+E29/(1+$A78)^(3+0.8)+F29/(1+$A78)^(4+0.8)+G29/(1+$A78)^(5+0.8)+H29/(1+$A78)^(6+0.8)+I29/(1+$A78)^(7+0.8)+J29/(1+$A78)^(8+0.8)+K29/(1+$A78)^(9+0.8))+K29*(1+C$73)/($A78-C$73)/(1+$A78)^9.8+Annahmen!B4)/Annahmen!B3 -> 140.56813 | D78: =((B29/(1+$A78)^(0+0.8)+C29/(1+$A78)^(1+0.8)+D29/(1+$A78)^(2+0.8)+E29/(1+$A78)^(3+0.8)+F29/(1+$A78)^(4+0.8)+G29/(1+$A78)^(5+0.8)+H29/(1+$A78)^(6+0.8)+I29/(1+$A78)^(7+0.8)+J29/(1+$A78)^(8+0.8)+K29/(1+$A78)^(9+0.8))+K29*(1+D$73)/($A78-D$73)/(1+$A78)^9.8+Annahmen!B4)/Annahmen!B3 -> 147.44118 | E78: =((B29/(1+$A78)^(0+0.8)+C29/(1+$A78)^(1+0.8)+D29/(1+$A78)^(2+0.8)+E29/(1+$A78)^(3+0.8)+F29/(1+$A78)^(4+0.8)+G29/(1+$A78)^(5+0.8)+H29/(1+$A78)^(6+0.8)+I29/(1+$A78)^(7+0.8)+J29/(1+$A78)^(8+0.8)+K29/(1+$A78)^(9+0.8))+K29*(1+E$73)/($A78-E$73)/(1+$A78)^9.8+Annahmen!B4)/Annahmen!B3 -> 155.37161 | F78: =((B29/(1+$A78)^(0+0.8)+C29/(1+$A78)^(1+0.8)+D29/(1+$A78)^(2+0.8)+E29/(1+$A78)^(3+0.8)+F29/(1+$A78)^(4+0.8)+G29/(1+$A78)^(5+0.8)+H29/(1+$A78)^(6+0.8)+I29/(1+$A78)^(7+0.8)+J29/(1+$A78)^(8+0.8)+K29/(1+$A78)^(9+0.8))+K29*(1+F$73)/($A78-F$73)/(1+$A78)^9.8+Annahmen!B4)/Annahmen!B3 -> 164.62379

Sheet Vergleich
A1: Unternehmen | B1: Ticker | C1: KGV fwd | D1: EV/EBITDA fwd | E1: Umsatzwachstum (ca.) | F1: Dividendenrendite | G1: Hinweis
A2: Zscaler | B2: ZS | C2: =Annahmen!B17 -> 45.844262 | D2: =Annahmen!B18 -> 31.271612 | E2: 0.17 | F2: =Annahmen!B22 -> 0 | G2: berechnet, Kurs 223,72 USD
A3: CrowdStrike | B3: CRWD | C3: 199 | D3: 151 | E3: 0.25 | F3: 0 | G3: eigene Analyse 16.10.2026
A4: Palo Alto Networks | B4: PANW | C4: 91 | D4: 67 | E4: 0.235 | F4: 0 | G4: eigene Analyse 16.10.2026 (inkl. Zukäufe)
A5: Fortinet | B5: FTNT | C5: 38 | D5: 30 | E5: 0.13 | F5: 0 | G5: GESCHÄTZT (Koala Gains, ~Aug. 2026)
A6: Check Point | B6: CHKP | C6: 20 | D6: 16 | E6: 0.06 | F6: 0 | G6: GESCHÄTZT (Koala Gains, Windsor Drake)
A7: Median Konkurrenten | C7: =MEDIAN(C3:C6) -> 64.5 | D7: =MEDIAN(D3:D6) -> 48.5 | E7: =MEDIAN(E3:E6) -> 0.1825 | F7: =MEDIAN(F3:F6) -> 0
A8: ZS Auf-/Abschlag ggü. Median | C8: =C2/C7-1 -> -0.28923624 | D8: =D2/D7-1 -> -0.3552245
A9: PEG (KGV / Gewinnwachstum ~16 %) | C9: =C2/16 -> 2.8652664
A11: Implizierter Kurs bei Peer-Median-KGV | C11: =C7*Annahmen!B9 -> 314.76
